<keymap version="1" name="mykeymap" parent="$default">
  <action id="Back">
    <keyboard-shortcut first-keystroke="ctrl alt left" />
    <mouse-shortcut keystroke="button4" />
    <keyboard-shortcut first-keystroke="alt h" />
  </action>
  <action id="BaseOnThisFunction" />
  <action id="CheckinProject" />
  <action id="CommentByLineComment">
    <keyboard-shortcut first-keystroke="ctrl slash" />
    <keyboard-shortcut first-keystroke="ctrl divide" />
    <keyboard-shortcut first-keystroke="alt q" />
  </action>
  <action id="EditorContextInfo" />
  <action id="EditorDown">
    <keyboard-shortcut first-keystroke="ctrl j" />
  </action>
  <action id="EditorUp">
    <keyboard-shortcut first-keystroke="up" />
    <keyboard-shortcut first-keystroke="ctrl k" />
  </action>
  <action id="FindInPath">
    <keyboard-shortcut first-keystroke="shift ctrl f" />
    <keyboard-shortcut first-keystroke="ctrl h" />
  </action>
  <action id="FindUsages">
    <keyboard-shortcut first-keystroke="alt f7" />
    <keyboard-shortcut first-keystroke="alt g" />
  </action>
  <action id="GotoClass">
    <keyboard-shortcut first-keystroke="ctrl n" />
    <keyboard-shortcut first-keystroke="alt #10000d6" />
  </action>
  <action id="GotoDeclaration">
    <keyboard-shortcut first-keystroke="ctrl b" />
    <mouse-shortcut keystroke="control button1" />
    <mouse-shortcut keystroke="button2" />
    <keyboard-shortcut first-keystroke="ctrl e" />
  </action>
  <action id="GuiDesigner.QuickJavadoc">
    <mouse-shortcut keystroke="alt button2" />
  </action>
  <action id="InsertLiveTemplate" />
  <action id="JumpToLastChange">
    <keyboard-shortcut first-keystroke="shift ctrl back_space" />
    <keyboard-shortcut first-keystroke="ctrl q" />
  </action>
  <action id="QuickJavaDoc">
    <mouse-shortcut keystroke="alt button2" />
  </action>
  <action id="RecentFiles" />
  <action id="RenameElement">
    <keyboard-shortcut first-keystroke="shift f6" />
    <keyboard-shortcut first-keystroke="shift alt r" />
  </action>
  <action id="Rerun">
    <keyboard-shortcut first-keystroke="ctrl f5" />
    <keyboard-shortcut first-keystroke="ctrl alt r" />
  </action>
  <action id="RerunTests" />
  <action id="SelectNextOccurrence" />
  <action id="TypeHierarchy" />
  <action id="TypeHierarchy.BaseOnThisType" />
  <action id="TypeHierarchyBase.BaseOnThisType" />
  <action id="Vcs.ShowMessageHistory">
    <keyboard-shortcut first-keystroke="ctrl m" />
  </action>
</keymap>